mlb/__init__.py
mlb/constants/__init__.py
mlb/constants/conferences.py
mlb/constants/datatypes.py
mlb/constants/divisions.py
mlb/constants/leagues.py
mlb/constants/sports.py
mlb/constants/teams.py
mlb/constants/vendors.py
mlb/dsp/__init__.py
mlb/dsp/auth.py
mlb/dsp/endpoints.py
mlb/dsp/settings.py
mlb/dsp/models/__init__.py
mlb/statsapi/__init__.py
mlb/statsapi/authentication.py
mlb/statsapi/endpoints.py
mlb/statsapi/settings.py
mlb/statsapi/models/__init__.py
mlb/statsapi/models/common.py
mlb/statsapi/models/game.py
mlb/statsapi/models/schedule.py
mlb/statsapi/models/weather.py
mlb_sdk-1.1.1.dist-info/LICENSE
mlb_sdk-1.1.1.dist-info/METADATA
mlb_sdk-1.1.1.dist-info/WHEEL
mlb_sdk-1.1.1.dist-info/top_level.txt
mlb_sdk-1.1.1.dist-info/RECORD
