Metadata-Version: 2.1
Name: mlb-sdk
Version: 1.1.1
Summary: Python wrapper for MLB APIs
Author: Ryan Schreiber
Author-email: ryanschreiber86@gmail.com
Project-URL: Documentation, https://github.com/mlb-sdk/python-mlb-sdk/
Project-URL: Source, https://github.com/mlb-sdk/python-mlb-sdk/
Project-URL: Tracker, https://github.com/mlb-sdk/python-mlb-sdk/issues
Keywords: mlb major league baseball sdk mlb-sdk sports professional
Classifier: Programming Language :: Python :: 3
Classifier: Operating System :: OS Independent
Requires-Python: >=3.0
License-File: LICENSE
Requires-Dist: requests
